statsdmetrics/__init__.py
statsdmetrics/metrics.py
statsdmetrics/client/__init__.py
statsdmetrics/client/tcp.py
statsdmetrics/client/timing.py
statsdmetrics-2.0.2.dist-info/METADATA
statsdmetrics-2.0.2.dist-info/RECORD
statsdmetrics-2.0.2.dist-info/WHEEL
statsdmetrics-2.0.2.dist-info/top_level.txt
statsdmetrics-2.0.2.dist-info/zip-safe
