Metadata-Version: 2.1
Name: statsdmetrics
Version: 2.0.2
Summary: Statsd metrics classes and clients
Home-page: https://github.com/farzadghanei/statsd-metrics
Author: Farzad Ghanei
Author-email: farzad.ghanei@gmail.com
License: MIT
Keywords: statsd metrics client
Platform: UNKNOWN
Classifier: Development Status :: 5 - Production/Stable
Classifier: Intended Audience :: Developers
Classifier: License :: OSI Approved :: MIT License
Classifier: Operating System :: OS Independent
Classifier: Programming Language :: Python
Classifier: Programming Language :: Python :: 2
Classifier: Programming Language :: Python :: 2.7
Classifier: Programming Language :: Python :: 3
Classifier: Programming Language :: Python :: 3.4
Classifier: Programming Language :: Python :: 3.5
Classifier: Programming Language :: Python :: 3.6
Classifier: Programming Language :: Python :: 3.7
Classifier: Programming Language :: Python :: Implementation :: CPython
Classifier: Programming Language :: Python :: Implementation :: PyPy
Classifier: Programming Language :: Python :: Implementation :: Jython
Classifier: Topic :: Software Development :: Libraries :: Python Modules
Classifier: Topic :: System :: Networking :: Monitoring
Provides-Extra: dev
Requires-Dist: pytest; extra == 'dev'
Requires-Dist: mock; extra == 'dev'
Requires-Dist: typing; extra == 'dev'
